{
  "_class": "group",
  "booleanOperation": 0,
  "do_objectID": "68CD2D3A-2E80-4320-86BD-04AFD73A2BC0",
  "exportOptions": {
    "_class": "exportOptions",
    "exportFormats": [
    ],
    "includedLayerIds": [
    ],
    "layerOptions": 0,
    "shouldTrim": false
  },
  "frame": {
    "_class": "rect",
    "constrainProportions": false,
    "height": 188,
    "width": 320,
    "x": -1,
    "y": -1
  },
  "hasClickThrough": false,
  "isFixedToViewport": false,
  "isFlippedHorizontal": false,
  "isFlippedVertical": false,
  "isLocked": false,
  "isVisible": true,
  "layerListExpandedType": 2,
  "layers": [
    {
      "class": "bitmap",
      "id": "F7118F6E-3716-4D73-A0F6-820B3F45E4C9"
    },
    {
      "class": "shapeGroup",
      "id": "D03F6E44-1961-4852-BF12-583A69E9BC6C"
    },
    {
      "class": "text",
      "id": "BD807C53-6CD2-4963-8B59-0037FAE2BB1D"
    }
  ],
  "name": "button3 copy 2",
  "nameIsFixed": true,
  "resizingConstraint": 63,
  "resizingType": 0,
  "rotation": 0,
  "shouldBreakMaskChain": false,
  "style": {
    "_class": "style",
    "endMarkerType": 0,
    "miterLimit": 10,
    "startMarkerType": 0,
    "windingRule": 1
  }
}